{
    "version": "39.40",
    "mainKey": "0x67E127D5C846A0D426BE4849FF4D087787CC0169D8BB461D69CF9B2B76AB21EC",
    "dynamicKeys": [
        {
            "name": "pakchunk1012-WindowsClient.utoc",
            "key": "0x50878EBFFB60AAF39529E3A8467BEAF453E4984002E76E3C30BF476CAB7B4C2F",
            "guid": "D8DB8B7F59E5E0BB2502D05F7CA26390",
            "keychain": "D8DB8B7F59E5E0BB2502D05F7CA26390:UIeOv/tgqvOVKeOoRnvq9FPkmEAC5248ML9HbKt7TC8=",
            "fileCount": 314,
            "hasHighResTextures": true,
            "size": {
                "raw": 30531030,
                "formatted": "29.1 MB"
            }
        }
    ],
    "unloaded": [
        {
            "name": "pakchunk1001-WindowsClient.utoc",
            "guid": "1701A7757F103D484D584F3E87152708",
            "fileCount": 190,
            "hasHighResTextures": true,
            "size": {
                "raw": 8943926,
                "formatted": "8.5 MB"
            }
        },
        {
            "name": "pakchunk1002-WindowsClient.utoc",
            "guid": "249B130C31906DBC2574108F774E70F2",
            "fileCount": 22,
            "hasHighResTextures": false,
            "size": {
                "raw": 1114902,
                "formatted": "1.1 MB"
            }
        },
        {
            "name": "pakchunk1003-WindowsClient.utoc",
            "guid": "4D2BAE4A8CD955329FA3C6337EEDBBAA",
            "fileCount": 35,
            "hasHighResTextures": false,
            "size": {
                "raw": 1377492,
                "formatted": "1.3 MB"
            }
        },
        {
            "name": "pakchunk1004-WindowsClient.utoc",
            "guid": "52A8755A11B1FEA5458568D45D8FFE7A",
            "fileCount": 104,
            "hasHighResTextures": true,
            "size": {
                "raw": 5444630,
                "formatted": "5.2 MB"
            }
        },
        {
            "name": "pakchunk1005-WindowsClient.utoc",
            "guid": "971B1E90F4B91D6FB3234BC1A32D5C57",
            "fileCount": 12,
            "hasHighResTextures": false,
            "size": {
                "raw": 735670,
                "formatted": "718.4 KB"
            }
        },
        {
            "name": "pakchunk1006-WindowsClient.utoc",
            "guid": "972E706DBCB3870225E65429223897EC",
            "fileCount": 146,
            "hasHighResTextures": true,
            "size": {
                "raw": 5041110,
                "formatted": "4.8 MB"
            }
        },
        {
            "name": "pakchunk1007-WindowsClient.utoc",
            "guid": "A194ADA8F3188F89CB93AB2FF3E34FED",
            "fileCount": 4,
            "hasHighResTextures": false,
            "size": {
                "raw": 1127686,
                "formatted": "1.1 MB"
            }
        },
        {
            "name": "pakchunk1008-WindowsClient.utoc",
            "guid": "A7853ADD0BA9539A20144F375969B68E",
            "fileCount": 25,
            "hasHighResTextures": false,
            "size": {
                "raw": 2685780,
                "formatted": "2.6 MB"
            }
        },
        {
            "name": "pakchunk1009-WindowsClient.utoc",
            "guid": "C0E87C4A78F6708EBF7C66E1D1694D31",
            "fileCount": 22,
            "hasHighResTextures": false,
            "size": {
                "raw": 1073830,
                "formatted": "1.0 MB"
            }
        },
        {
            "name": "pakchunk1010-WindowsClient.utoc",
            "guid": "C755CFF0092A1DE63DE98F9C5A10E9BC",
            "fileCount": 864,
            "hasHighResTextures": true,
            "size": {
                "raw": 40873238,
                "formatted": "39.0 MB"
            }
        },
        {
            "name": "pakchunk1011-WindowsClient.utoc",
            "guid": "D3A8927824A278B41BC13105C7E6B2B9",
            "fileCount": 31,
            "hasHighResTextures": false,
            "size": {
                "raw": 2005784,
                "formatted": "1.9 MB"
            }
        },
        {
            "name": "pakchunk1013-WindowsClient.utoc",
            "guid": "DBCAA577BD017AC8CAB2FA6E6182E893",
            "fileCount": 113,
            "hasHighResTextures": true,
            "size": {
                "raw": 8650596,
                "formatted": "8.2 MB"
            }
        },
        {
            "name": "pakchunk1014-WindowsClient.utoc",
            "guid": "DDABCDCAA37175C12D4732F1F5F3E232",
            "fileCount": 513,
            "hasHighResTextures": true,
            "size": {
                "raw": 34445988,
                "formatted": "32.9 MB"
            }
        }
    ]
}